[
  {
    "time": "2025-12-19 12:25:33",
    "username": "htios2590",
    "name": "Hữu",
    "action": "START"
  },
  {
    "time": "2025-12-19 12:26:26",
    "username": "htios2590",
    "name": "ACB ONE",
    "action": "UPLOAD ACB ONE.ipa"
  },
  {
    "time": "2025-12-19 12:29:20",
    "username": "htios2590",
    "name": "Hữu",
    "action": "START"
  },
  {
    "time": "2025-12-19 12:33:41",
    "username": "htios2590",
    "name": "Hữu",
    "action": "START"
  },
  {
    "time": "2025-12-19 12:34:28",
    "username": "htios2590",
    "name": "TPBank Mobile",
    "action": "UPLOAD TPBank Mobile.ipa"
  },
  {
    "time": "2025-12-19 12:43:23",
    "username": "htios2590",
    "name": "Hữu",
    "action": "START"
  },
  {
    "time": "2025-12-19 12:44:08",
    "username": "htios2590",
    "name": "Agribank",
    "action": "UPLOAD Agribank.ipa"
  },
  {
    "time": "2025-12-19 13:19:23",
    "username": "htios2590",
    "name": "Hữu",
    "action": "START"
  }
]